myconfig/__init__.py
myconfig/config.py
myconfig/logs.py
myconfig/yamlext.py
myconfig4app-1.3.1.dist-info/WHEEL
myconfig4app-1.3.1.dist-info/METADATA
myconfig4app-1.3.1.dist-info/RECORD
