Metadata-Version: 2.1
Name: myconfig4app
Version: 1.3.1
Summary: 
License: MIT
Author: icersong
Author-email: icersong@gmail.com
Requires-Python: >=3.7,<4.0
Classifier: License :: OSI Approved :: MIT License
Classifier: Programming Language :: Python :: 3
Classifier: Programming Language :: Python :: 3.7
Classifier: Programming Language :: Python :: 3.8
Classifier: Programming Language :: Python :: 3.9
Classifier: Programming Language :: Python :: 3.10
Classifier: Programming Language :: Python :: 3.11
Requires-Dist: concurrent-log-handler (>=0.9.20,<0.10.0)
Requires-Dist: path (>=16.4.0,<17.0.0)
Requires-Dist: pyyaml (>=6.0,<7.0)
Requires-Dist: singleton-decorator (>=1.0.0,<2.0.0)
